{"cameraMode":{"drawMode":0,"name":"Shaded","section":"Shading Mode"},"sceneLighting":true,"audioPlay":false,"sceneViewState":{"m_AlwaysRefresh":false,"showFog":true,"showSkybox":true,"showFlares":true,"showImageEffects":true,"showParticleSystems":true,"showVisualEffectGraphs":true,"m_FxEnabled":true},"in2DMode":false,"pivot":{"x":3.1447830200195314,"y":-12.03369140625,"z":-0.08905601501464844},"rotation":{"x":0.1552215963602066,"y":0.8018707036972046,"z":-0.2365049570798874,"w":0.5262794494628906},"size":32.6362419128418,"orthographic":false}